equanimus_llm_orchestrator/__init__.py
equanimus_llm_orchestrator/run_chat.py
equanimus_llm_orchestrator/settings.py
equanimus_llm_orchestrator/adapters/__init__.py
equanimus_llm_orchestrator/adapters/aws.py
equanimus_llm_orchestrator/adapters/huggingface.py
equanimus_llm_orchestrator/adapters/ollama.py
equanimus_llm_orchestrator/adapters/openai.py
equanimus_llm_orchestrator/adapters/setup.py
equanimus_llm_orchestrator/agents/__init__.py
equanimus_llm_orchestrator/agents/clone_workflow.py
equanimus_llm_orchestrator/agents/copilot_workflow.py
equanimus_llm_orchestrator/agents/main_workflow.py
equanimus_llm_orchestrator/agents/rag_workflow.py
equanimus_llm_orchestrator/agents/summarization_workflow.py
equanimus_llm_orchestrator/agents/edges/__init__.py
equanimus_llm_orchestrator/agents/edges/copilot_edges.py
equanimus_llm_orchestrator/agents/edges/main_edges.py
equanimus_llm_orchestrator/agents/edges/rag_edges.py
equanimus_llm_orchestrator/agents/edges/summary_doc_edges.py
equanimus_llm_orchestrator/agents/nodes/__init__.py
equanimus_llm_orchestrator/agents/nodes/clone_chat_nodes.py
equanimus_llm_orchestrator/agents/nodes/copilot_nodes.py
equanimus_llm_orchestrator/agents/nodes/main_nodes.py
equanimus_llm_orchestrator/agents/nodes/rag_nodes.py
equanimus_llm_orchestrator/agents/nodes/summary_doc_nodes.py
equanimus_llm_orchestrator/agents/states/__init__.py
equanimus_llm_orchestrator/agents/states/clone_state.py
equanimus_llm_orchestrator/agents/states/copilot_state.py
equanimus_llm_orchestrator/agents/states/main_state.py
equanimus_llm_orchestrator/agents/states/rag_state.py
equanimus_llm_orchestrator/agents/states/summarizations_state.py
equanimus_llm_orchestrator/chat_prompts/__init__.py
equanimus_llm_orchestrator/chat_prompts/templates_prompts.py
equanimus_llm_orchestrator/connectVDB/__init__.py
equanimus_llm_orchestrator/connectVDB/connectCroma.py
equanimus_llm_orchestrator/core/_init_.py
equanimus_llm_orchestrator/core/clone_chat.py
equanimus_llm_orchestrator-1.0.0.dist-info/METADATA
equanimus_llm_orchestrator-1.0.0.dist-info/WHEEL
equanimus_llm_orchestrator-1.0.0.dist-info/top_level.txt
equanimus_llm_orchestrator-1.0.0.dist-info/RECORD
